graph_jpr-0.1.1.dist-info/METADATA
graph_jpr-0.1.1.dist-info/WHEEL
graph_jpr-0.1.1.dist-info/license_files/LICENSE
graph_jpr/__init__.py
graph_jpr/graph_jpr.cp312-win_amd64.pyd
graph_jpr-0.1.1.dist-info/RECORD
